mandarina/__init__.py
mandarina/base.py
mandarina/benchmark.py
mandarina/csv.py
mandarina/file.py
mandarina/graph.py
mandarina/image.py
mandarina/math.py
mandarina/ml.py
mandarina/options.py
mandarina/randomdata.py
mandarina/scheduling.py
mandarina-0.1.1.dist-info/METADATA
mandarina-0.1.1.dist-info/WHEEL
mandarina-0.1.1.dist-info/licenses/LICENSE
mandarina-0.1.1.dist-info/RECORD
