Metadata-Version: 2.1
Name: mandarina
Version: 0.1.1
Summary: Friendly data science library
Author-email: Alen Frey <mailtoalenf@gmail.com>
License-File: LICENSE
Classifier: License :: OSI Approved :: MIT License
Classifier: Operating System :: OS Independent
Classifier: Programming Language :: Python :: 3
Requires-Python: >=3.7
